schedulefree/__init__.py
schedulefree/adamw_schedulefree.py
schedulefree/adamw_schedulefree_closure.py
schedulefree/adamw_schedulefree_paper.py
schedulefree/adamw_schedulefree_reference.py
schedulefree/radam_schedulefree.py
schedulefree/radam_schedulefree_closure.py
schedulefree/sgd_schedulefree.py
schedulefree/sgd_schedulefree_closure.py
schedulefree/sgd_schedulefree_reference.py
schedulefree/test_schedulefree.py
schedulefree/wrap_schedulefree.py
schedulefree/wrap_schedulefree_reference.py
schedulefree/algoperf/external_tuning/schedule_free_adamw/requirements.txt
schedulefree/algoperf/external_tuning/schedule_free_adamw/submission.py
schedulefree/algoperf/external_tuning/schedule_free_adamw/tuning_search_space.json
schedulefree/algoperf/external_tuning/schedule_free_prodigy/requirements.txt
schedulefree/algoperf/external_tuning/schedule_free_prodigy/submission.py
schedulefree/algoperf/external_tuning/schedule_free_prodigy/tuning_search_space.json
schedulefree/algoperf/self_tuning/schedule_free_adamw/requirements.txt
schedulefree/algoperf/self_tuning/schedule_free_adamw/submission.py
schedulefree-1.4.1.dist-info/METADATA
schedulefree-1.4.1.dist-info/WHEEL
schedulefree-1.4.1.dist-info/licenses/LICENSE
schedulefree-1.4.1.dist-info/RECORD
