Metadata-Version: 2.4
Name: schedulefree
Version: 1.4.1
Summary: Schedule Free Learning in PyTorch
Project-URL: Source, https://github.com/facebookresearch/schedule_free
Author-email: Aaron Defazio <adefazio@meta.com>
License-File: LICENSE
Classifier: License :: OSI Approved :: Apache Software License
Classifier: Operating System :: OS Independent
Classifier: Programming Language :: Python :: 3
Requires-Python: >=3.4
Requires-Dist: torch
Requires-Dist: typing-extensions
